ML_tools/__init__.py
ML_tools/slack_notifier.py
ML_tools-0.0.7.dist-info/METADATA
ML_tools-0.0.7.dist-info/WHEEL
ML_tools-0.0.7.dist-info/top_level.txt
ML_tools-0.0.7.dist-info/RECORD
